ciplog/__init__.py
ciplog/cip_log.py
ciplog/cip_log_new_format.py
ciplog/json_log_formatter.py
ciplog/v2/__init__.py
ciplog/v2/json_log_formatter.py
ciplog/v2/new_log.py
test/__init__.py
test/cip_log_new_format.py
test/cip_log_v2_new_log.py
test/test_cip_log.py
ciplog-1.1.8.dist-info/METADATA
ciplog-1.1.8.dist-info/WHEEL
ciplog-1.1.8.dist-info/top_level.txt
ciplog-1.1.8.dist-info/RECORD
