Metadata-Version: 2.1
Name: ciplog
Version: 1.1.8
Summary: TCIP logging class.
Home-page: UNKNOWN
Author: Adriano Canofre
Author-email: adrianoknofre@gmail.com
License: MIT
Platform: UNKNOWN
